verilog_tp4/assist_control.v
// Decisao de assistencia na FPGA.
// Freio: atencao/critico no centro. Seta: livre, depois atencao.
// saida_segura so veta se o obstaculo aproximar >= 10 cm (caso extremo).

module assist_control #(
    parameter REDUC_ATENCAO = 8'd20,
    parameter REDUC_CRITICO = 8'd40,
    parameter signed [7:0] LIMIAR_SAIDA = -8'sd10
) (
    input  wire [7:0] dist_e,
    input  wire [7:0] dist_c,
    input  wire [7:0] dist_d,
    input  wire signed [7:0] vel_e,
    input  wire signed [7:0] vel_c,
    input  wire signed [7:0] vel_d,
    input  wire [7:0] vel_atual,
    input  wire [7:0] cfg_dist_free,
    input  wire [7:0] cfg_dist_att,
    input  wire [7:0] cfg_vel_max,
    output reg  [7:0] vel_rec,
    output reg  [1:0] dir_fuga
);

    wire zona_livre_e = (dist_e > cfg_dist_free);
    wire zona_livre_c = (dist_c > cfg_dist_free);
    wire zona_livre_d = (dist_d > cfg_dist_free);

    wire zona_atencao_e = !zona_livre_e && (dist_e >= cfg_dist_att);
    wire zona_atencao_c = !zona_livre_c && (dist_c >= cfg_dist_att);
    wire zona_atencao_d = !zona_livre_d && (dist_d >= cfg_dist_att);
    wire zona_critico_c = !zona_livre_c && !zona_atencao_c;

    wire saida_segura_e = (vel_e > LIMIAR_SAIDA);
    wire saida_segura_c = (vel_c > LIMIAR_SAIDA);
    wire saida_segura_d = (vel_d > LIMIAR_SAIDA);

    wire [7:0] reducao =
        zona_critico_c ? REDUC_CRITICO :
        zona_atencao_c ? REDUC_ATENCAO :
        8'd0;

    wire [7:0] vel_base = (vel_atual < cfg_vel_max) ? vel_atual : cfg_vel_max;
    wire signed [8:0] vel_tmp = vel_base - reducao;
    wire [7:0] vel_clamped =
        (vel_tmp <= 9'sd0) ? 8'd0 : vel_tmp[7:0];

    always @(*) begin
        vel_rec = vel_clamped;

        // Normal: cfg (livre > atencao). saida_segura so barra aproximacao extrema.
        if (zona_livre_c && saida_segura_c)
            dir_fuga = 2'b00;
        else if (zona_livre_e && saida_segura_e)
            dir_fuga = 2'b01;
        else if (zona_livre_d && saida_segura_d)
            dir_fuga = 2'b10;
        else if (zona_atencao_c && saida_segura_c)
            dir_fuga = 2'b00;
        else if (zona_atencao_e && saida_segura_e)
            dir_fuga = 2'b01;
        else if (zona_atencao_d && saida_segura_d)
            dir_fuga = 2'b10;
        else
            dir_fuga = 2'b11;
    end

endmodule

verilog_tp4/tb/assist_control_tb.v
`timescale 1ns / 1ps

module assist_control_tb;

    localparam [7:0] DIST_FREE = 8'd100;
    localparam [7:0] DIST_ATT  = 8'd50;
    localparam [7:0] VEL_MAX   = 8'd120;
    localparam [7:0] VEL_NOW   = 8'd80;

    localparam [1:0] FRENTE   = 2'b00;
    localparam [1:0] ESQUERDA = 2'b01;
    localparam [1:0] DIREITA  = 2'b10;
    localparam [1:0] TRAS     = 2'b11;

    reg  [7:0] dist_e, dist_c, dist_d;
    reg  signed [7:0] vel_e, vel_c, vel_d;
    reg  [7:0] vel_atual;
    reg  [7:0] cfg_dist_free, cfg_dist_att, cfg_vel_max;
    wire [7:0] vel_rec;
    wire [1:0] dir_fuga;

    integer erros;

    assist_control dut (
        .dist_e        (dist_e),
        .dist_c        (dist_c),
        .dist_d        (dist_d),
        .vel_e         (vel_e),
        .vel_c         (vel_c),
        .vel_d         (vel_d),
        .vel_atual     (vel_atual),
        .cfg_dist_free (cfg_dist_free),
        .cfg_dist_att  (cfg_dist_att),
        .cfg_vel_max   (cfg_vel_max),
        .vel_rec       (vel_rec),
        .dir_fuga      (dir_fuga)
    );

    task apply;
        input [7:0] e, c, d;
        input signed [7:0] ve, vc, vd;
        begin
            dist_e = e; dist_c = c; dist_d = d;
            vel_e  = ve; vel_c = vc; vel_d = vd;
            #1;
        end
    endtask

    task check;
        input [1:0]   exp_dir;
        input [7:0]   exp_vel;
        input [255:0] name;
        begin
            if (dir_fuga === exp_dir && vel_rec === exp_vel)
                $display("OK   %0s: dir=%0d vel_rec=%0d", name, dir_fuga, vel_rec);
            else begin
                $display("FAIL %0s: dir=%0d (exp %0d) vel_rec=%0d (exp %0d)",
                         name, dir_fuga, exp_dir, vel_rec, exp_vel);
                erros = erros + 1;
            end
        end
    endtask

    initial begin
        $dumpfile("tb/assist_control_tb.vcd");
        $dumpvars(0, assist_control_tb);

        erros = 0;
        cfg_dist_free = DIST_FREE;
        cfg_dist_att  = DIST_ATT;
        cfg_vel_max   = VEL_MAX;
        vel_atual     = VEL_NOW;

        // 1. Centro livre, ninguem fecha
        apply(8'd120, 8'd140, 8'd110, 8'sd0, 8'sd4, 8'sd0);
        check(FRENTE, 8'd80, "1 livre C, sem fechar");

        // 2. Centro atencao, esquerda livre
        apply(8'd130, 8'd70, 8'd40, 8'sd0, 8'sd0, 8'sd0);
        check(ESQUERDA, 8'd60, "2 C atencao, E livre");

        // 3. Ninguem livre; C e E atencao
        apply(8'd60, 8'd70, 8'd40, 8'sd0, 8'sd0, 8'sd0);
        check(FRENTE, 8'd60, "3 so atencao, prefere C");

        // 4. C livre mas fecha forte; E atencao segura
        apply(8'd80, 8'd150, 8'd40, 8'sd2, -8'sd18, 8'sd0);
        check(ESQUERDA, 8'd80, "4 veto C (vel=-18), E atencao");

        // 5. Tudo critico
        apply(8'd25, 8'd25, 8'd25, -8'sd3, 8'sd0, 8'sd1);
        check(TRAS, 8'd40, "5 tudo critico");

        // 6. Tudo atencao, D fecha
        apply(8'd70, 8'd65, 8'd55, 8'sd0, 8'sd0, -8'sd25);
        check(FRENTE, 8'd60, "6 atencao, D vetada");

        // 7. So D livre
        apply(8'd30, 8'd20, 8'd120, -8'sd12, -8'sd20, 8'sd0);
        check(DIREITA, 8'd40, "7 so D livre");

        // 8. vel=0 (antes de 4 ecos): so cfg
        apply(8'd40, 8'd140, 8'd40, 8'sd0, 8'sd0, 8'sd0);
        check(FRENTE, 8'd80, "8 vel=0, C livre");

        // 9. Limiar: -9 ainda seguro
        apply(8'd40, 8'd140, 8'd40, 8'sd0, -8'sd9, 8'sd0);
        check(FRENTE, 8'd80, "9 vel_c=-9 ainda segura");

        // 10. Limiar: -10 veta o centro livre
        apply(8'd80, 8'd140, 8'd40, 8'sd0, -8'sd10, 8'sd0);
        check(ESQUERDA, 8'd80, "10 vel_c=-10 veta C, E atencao");

        // 11. vel_atual acima do teto do Pi
        vel_atual = 8'd200;
        apply(8'd120, 8'd140, 8'd110, 8'sd0, 8'sd0, 8'sd0);
        check(FRENTE, VEL_MAX, "11 base = min(atual, vel_max)");

        // 12. Critico com atual < reducao → satura em 0
        vel_atual = 8'd30;
        apply(8'd20, 8'd20, 8'd20, 8'sd0, 8'sd0, 8'sd0);
        check(TRAS, 8'd0, "12 30-40 satura em 0");

        if (erros == 0)
            $display("assist_control: %0d testes OK", 12);
        else
            $display("assist_control: %0d FALHAS", erros);

        $finish;
    end

endmodule

verilog_tp4/tb/assist_control_tb.vcd
$date
	Sun Aug 30 14:01:44 2026
$end
$version
	Icarus Verilog
$end
$timescale
	1ps
$end
$scope module assist_control_tb $end
$var wire 8 ! vel_rec [7:0] $end
$var wire 2 " dir_fuga [1:0] $end
$var reg 8 # cfg_dist_att [7:0] $end
$var reg 8 $ cfg_dist_free [7:0] $end
$var reg 8 % cfg_vel_max [7:0] $end
$var reg 8 & dist_c [7:0] $end
$var reg 8 ' dist_d [7:0] $end
$var reg 8 ( dist_e [7:0] $end
$var reg 8 ) vel_atual [7:0] $end
$var reg 8 * vel_c [7:0] $end
$var reg 8 + vel_d [7:0] $end
$var reg 8 , vel_e [7:0] $end
$var integer 32 - erros [31:0] $end
$scope module dut $end
$var wire 8 . cfg_dist_att [7:0] $end
$var wire 8 / cfg_dist_free [7:0] $end
$var wire 8 0 cfg_vel_max [7:0] $end
$var wire 8 1 dist_c [7:0] $end
$var wire 8 2 dist_d [7:0] $end
$var wire 8 3 dist_e [7:0] $end
$var wire 8 4 vel_atual [7:0] $end
$var wire 8 5 vel_c [7:0] $end
$var wire 8 6 vel_d [7:0] $end
$var wire 8 7 vel_e [7:0] $end
$var wire 1 8 zona_atencao_c $end
$var wire 1 9 zona_atencao_d $end
$var wire 1 : zona_atencao_e $end
$var wire 1 ; zona_critico_c $end
$var wire 1 < zona_livre_e $end
$var wire 1 = zona_livre_d $end
$var wire 1 > zona_livre_c $end
$var wire 9 ? vel_tmp [8:0] $end
$var wire 8 @ vel_clamped [7:0] $end
$var wire 8 A vel_base [7:0] $end
$var wire 1 B saida_segura_e $end
$var wire 1 C saida_segura_d $end
$var wire 1 D saida_segura_c $end
$var wire 8 E reducao [7:0] $end
$var reg 2 F dir_fuga [1:0] $end
$var reg 8 G vel_rec [7:0] $end
$upscope $end
$scope task apply $end
$var reg 8 H c [7:0] $end
$var reg 8 I d [7:0] $end
$var reg 8 J e [7:0] $end
$var reg 8 K vc [7:0] $end
$var reg 8 L vd [7:0] $end
$var reg 8 M ve [7:0] $end
$upscope $end
$scope task check $end
$var reg 2 N exp_dir [1:0] $end
$var reg 8 O exp_vel [7:0] $end
$var reg 256 P name [255:0] $end
$upscope $end
$upscope $end
$enddefinitions $end
#0
$dumpvars
bx P
bx O
bx N
b0 M
b0 L
b100 K
b1111000 J
b1101110 I
b10001100 H
b1010000 G
b0 F
b0 E
1D
1C
1B
b1010000 A
b1010000 @
b1010000 ?
1>
1=
1<
0;
0:
09
08
b0 7
b0 6
b100 5
b1010000 4
b1111000 3
b1101110 2
b10001100 1
b1111000 0
b1100100 /
b110010 .
b0 -
b0 ,
b0 +
b100 *
b1010000 )
b1111000 (
b1101110 '
b10001100 &
b1111000 %
b1100100 $
b110010 #
b0 "
b1010000 !
$end
#1000
b111100 !
b111100 G
b111100 @
b111100 ?
b10100 E
18
0;
b1 "
b1 F
b0 *
b0 5
0=
b101000 '
b101000 2
0>
b1000110 &
b1000110 1
b10000010 (
b10000010 3
b0 K
b101000 I
b1000110 H
b10000010 J
b1100010010000001101100011010010111011001110010011001010010000001000011001011000010000001110011011001010110110100100000011001100110010101100011011010000110000101110010 P
b1010000 O
b0 N
#2000
1:
b0 "
b0 F
0<
b111100 (
b111100 3
b111100 J
b11001000100000010000110010000001100001011101000110010101101110011000110110000101101111001011000010000001000101001000000110110001101001011101100111001001100101 P
b111100 O
b1 N
#3000
b1010000 !
b1010000 G
b1010000 @
b1010000 ?
b0 E
08
b1 "
b1 F
0D
b11101110 *
b11101110 5
b10 ,
b10 7
1>
b10010110 &
b10010110 1
b1010000 (
b1010000 3
b11101110 K
b10 M
b10010110 H
b1010000 J
b11001100100000011100110110111100100000011000010111010001100101011011100110001101100001011011110010110000100000011100000111001001100101011001100110010101110010011001010010000001000011 P
b0 N
#4000
b101000 !
b101000 G
b101000 @
b101000 ?
b101000 E
1;
b11 "
b11 F
0:
b1 +
b1 6
1D
b0 *
b0 5
b11111101 ,
b11111101 7
b11001 '
b11001 2
0>
b11001 &
b11001 1
b11001 (
b11001 3
b1 L
b0 K
b11111101 M
b11001 I
b11001 H
b11001 J
b11010000100000011101100110010101110100011011110010000001000011001000000010100001110110011001010110110000111101001011010011000100111000001010010010110000100000010001010010000001100001011101000110010101101110011000110110000101101111 P
b1010000 O
b1 N
#5000
b111100 !
b111100 G
b111100 @
b111100 ?
b10100 E
0;
b0 "
b0 F
19
18
1:
0C
b11100111 +
b11100111 6
b0 ,
b0 7
b110111 '
b110111 2
b1000001 &
b1000001 1
b1000110 (
b1000110 3
b11100111 L
b0 M
b110111 I
b1000001 H
b1000110 J
b11010100100000011101000111010101100100011011110010000001100011011100100110100101110100011010010110001101101111 P
b101000 O
b11 N
#6000
b101000 !
b101000 G
b101000 @
b101000 ?
b101000 E
1;
09
b10 "
b10 F
08
0:
1C
b0 +
b0 6
0D
b11101100 *
b11101100 5
0B
b11110100 ,
b11110100 7
1=
b1111000 '
b1111000 2
b10100 &
b10100 1
b11110 (
b11110 3
b0 L
b11101100 K
b11110100 M
b1111000 I
b10100 H
b11110 J
b110110001000000110000101110100011001010110111001100011011000010110111100101100001000000100010000100000011101100110010101110100011000010110010001100001 P
b111100 O
b0 N
#7000
b1010000 !
b1010000 G
b1010000 @
b1010000 ?
b0 E
0;
b0 "
b0 F
1D
b0 *
b0 5
1B
b0 ,
b0 7
0=
b101000 '
b101000 2
1>
b10001100 &
b10001100 1
b101000 (
b101000 3
b0 K
b0 M
b101000 I
b10001100 H
b101000 J
b1101110010000001110011011011110010000001000100001000000110110001101001011101100111001001100101 P
b101000 O
b10 N
#8000
b11110111 *
b11110111 5
b11110111 K
b111000001000000111011001100101011011000011110100110000001011000010000001000011001000000110110001101001011101100111001001100101 P
b1010000 O
b0 N
#9000
b1 "
b1 F
1:
0D
b11110110 *
b11110110 5
b1010000 (
b1010000 3
b11110110 K
b1010000 J
b11100100100000011101100110010101101100010111110110001100111101001011010011100100100000011000010110100101101110011001000110000100100000011100110110010101100111011101010111001001100001 P
#10000
b1111000 !
b1111000 G
b1111000 @
0:
b0 "
b0 F
b1111000 ?
b1111000 A
1D
b0 *
b0 5
1=
b1101110 '
b1101110 2
1<
b1111000 (
b1111000 3
b0 K
b1101110 I
b1111000 J
b11001000 )
b11001000 4
b1100010011000000100000011101100110010101101100010111110110001100111101001011010011000100110000001000000111011001100101011101000110000100100000010000110010110000100000010001010010000001100001011101000110010101101110011000110110000101101111 P
b1 N
#11000
b0 !
b0 G
b0 @
b101000 E
1;
b11 "
b11 F
b111110110 ?
b11110 A
0=
b10100 '
b10100 2
0>
b10100 &
b10100 1
0<
b10100 (
b10100 3
b10100 I
b10100 H
b10100 J
b11110 )
b11110 4
b11000100110001001000000110001001100001011100110110010100100000001111010010000001101101011010010110111000101000011000010111010001110101011000010110110000101100001000000111011001100101011011000101111101101101011000010111100000101001 P
b1111000 O
b0 N
#12000
b11000100110010001000000011001100110000001011010011010000110000001000000111001101100001011101000111010101110010011000010010000001100101011011010010000000110000 P
b0 O
b11 N
